{
  "updated_at": "2026-06-19 08:16:54",
  "route": "89番 糸満線（上り）",
  "buses": [
    {
      "lat": 26.1361666666137,
      "lon": 127.673249999682,
      "plate": "沖縄200か1521",
      "company": "琉球バス交通"
    },
    {
      "lat": 26.2000666666652,
      "lon": 127.683950000008,
      "plate": "沖縄200か912",
      "company": "琉球バス交通"
    },
    {
      "lat": 26.206683333185,
      "lon": 127.686449999809,
      "plate": "沖縄200か1691",
      "company": "琉球バス交通"
    },
    {
      "lat": 26.164816666709,
      "lon": 127.669266666571,
      "plate": "沖縄230あ 1364",
      "company": "沖縄バス"
    },
    {
      "lat": 26.1993499999576,
      "lon": 127.684966666566,
      "plate": "沖縄230あ 1029",
      "company": "沖縄バス"
    },
    {
      "lat": 26.1892499997881,
      "lon": 127.662166666455,
      "plate": "沖縄200か1523",
      "company": "琉球バス交通"
    },
    {
      "lat": 26.2002999999788,
      "lon": 127.672566666603,
      "plate": "沖縄230あ 1362",
      "company": "沖縄バス"
    }
  ]
}